{
    "valid":true,
    "data":"{\"count\":51,\"data\":[{\"vendorEmail\":\"\",\"vendorID\":\"0000000045ebca930145eeded1fa00c9\",\"currencyid\":\"1\",\"vendorName\":\"COILCRAFT+INDUSTRIES+SINGAPORE+PTE+LTD\",\"vendorContactNo\":\"+65 62966933\",\"vendorDebitTerm\":\"0000000045e8029f0145ea49830e0003\",\"vendorAddress\":\"BLOCK+512+CHAI+CHEE+LANE+%2303-15+BEDOK+INDUSTRIAL+ESTATE+SINGAPORE+469028\",\"vendorActivateStatus\":true,\"vendorFax\":\"\"},{\"vendorEmail\":\"\",\"vendorID\":\"0000000045ebca930145eeded1f700c8\",\"currencyid\":\"1\",\"vendorName\":\"COILCRAFT+SINGAPORE+PTE+LTD\",\"vendorContactNo\":\"+65 62966933\",\"vendorDebitTerm\":\"0000000045e8029f0145ea49830e0003\",\"vendorAddress\":\"BLOCK+512+CHAI+CHEE+LANE+%2303-15+BEDOK+INDUSTRIAL+ESTATE+SINGAPORE+469028\",\"vendorActivateStatus\":true,\"vendorFax\":\"\"},{\"vendorEmail\":\"\",\"vendorID\":\"0000000045ebca930145eeded27100e7\",\"currencyid\":\"13\",\"vendorName\":\"CTC+INDONESIA\",\"vendorContactNo\":\"0778 290300\",\"vendorDebitTerm\":\"0000000045e8029f0145ea49830e0003\",\"vendorAddress\":\"JLN+MAWAR+BLK+C+NO+2+TAMAN+DOTAMANA+BATAM%2C+INDONESIA\",\"vendorActivateStatus\":true,\"vendorFax\":\"\"},{\"vendorEmail\":\"\",\"vendorID\":\"0000000045ebca930145eeded21d00d5\",\"currencyid\":\"13\",\"vendorName\":\"CV+.+ADITYA+PUTRA+BINTAN\",\"vendorContactNo\":\"08127078700\",\"vendorDebitTerm\":\"0000000045e8029f0145ea49830e0003\",\"vendorAddress\":\"PERUM+LOBAM+MAS+ASRI+BLOK+S%2F187+TANJUNG+PERMAI+%2C+BINTAN+29154%2C+INDONESIA\",\"vendorActivateStatus\":true,\"vendorFax\":\"\"},{\"vendorEmail\":\"\",\"vendorID\":\"0000000045ebca930145eeded27500e8\",\"currencyid\":\"13\",\"vendorName\":\"CV+KEBOEN+MANGGA\",\"vendorContactNo\":\"081364683070\",\"vendorDebitTerm\":\"0000000045e8029f0145ea49830e0003\",\"vendorAddress\":\"JL+INDUSTRI%2C+MEKARSARI+NO+1\",\"vendorActivateStatus\":false,\"vendorFax\":\"\"},{\"vendorEmail\":\"\",\"vendorID\":\"0000000045ebca930145eeded20600ce\",\"currencyid\":\"13\",\"vendorName\":\"CV.+ANSEL+FURNICENTRE\",\"vendorContactNo\":\"0771 483191\",\"vendorDebitTerm\":\"0000000045e8029f0145ea49830e0003\",\"vendorAddress\":\"JLN+INDUNSURI%2C+PASAR+BARU+NO.+1%2C2%2C3+TANJUNG+UBAN+KEPRI+29152%2C+INDONESIA\",\"vendorActivateStatus\":false,\"vendorFax\":\"\"},{\"vendorEmail\":\"\",\"vendorID\":\"0000000045ebca930145eeded25c00e2\",\"currencyid\":\"13\",\"vendorName\":\"CV.+BATAM+COPIER\",\"vendorContactNo\":\"0778 7028977/7494999\",\"vendorDebitTerm\":\"0000000045e8029f0145ea49830e0003\",\"vendorAddress\":\"LYTECH+INDUSTRIAL+PARK+C2+NO+2+BATAM+CENTRE%2C+INDONESIA\",\"vendorActivateStatus\":true,\"vendorFax\":\"\"},{\"vendorEmail\":\"\",\"vendorID\":\"0000000045ebca930145eeded21000d1\",\"currencyid\":\"13\",\"vendorName\":\"CV.+CAKRA+MANDIRI+%28IDR%29\",\"vendorContactNo\":\"0771 484218\",\"vendorDebitTerm\":\"0000000045e8029f0145ea49830e0003\",\"vendorAddress\":\"RUKO+KP.+HARAPAN+NO.2+TELUK+SASAH%2C+BINTAN%2C+INDONESIA\",\"vendorActivateStatus\":true,\"vendorFax\":\"\"},{\"vendorEmail\":\"\",\"vendorID\":\"0000000045ebca930145eeded29c00f1\",\"currencyid\":\"6\",\"vendorName\":\"CV.+CAKRA+MANDIRI+%28SGD%29\",\"vendorContactNo\":\"0771 484218\",\"vendorDebitTerm\":\"0000000045e8029f0145ea49830e0003\",\"vendorAddress\":\"RUKO+KP.+HARAPAN+NO.2+TELUK+SASAH%2C+BINTAN%2C+INDONESIA\",\"vendorActivateStatus\":true,\"vendorFax\":\"\"},{\"vendorEmail\":\"\",\"vendorID\":\"0000000045ebca930145eeded20400cd\",\"currencyid\":\"13\",\"vendorName\":\"CV.+ELANG+FLEKSINDO+%28IDR%29\",\"vendorContactNo\":\"0771 482730\",\"vendorDebitTerm\":\"0000000045e8029f0145ea49830e0003\",\"vendorAddress\":\"JLN.+PASAR+BARU+BLOK+A++NO.+6+TANJUNG+UBAN%2C+KEPRI%2C+INDONESIA\",\"vendorActivateStatus\":true,\"vendorFax\":\"\"},{\"vendorEmail\":\"\",\"vendorID\":\"0000000045ebca930145eeded29600f0\",\"currencyid\":\"6\",\"vendorName\":\"CV.+ELANG+FLEKSINDO%28SGD%29\",\"vendorContactNo\":\"0771 482730\",\"vendorDebitTerm\":\"0000000045e8029f0145ea49830e0003\",\"vendorAddress\":\"JLN.+PASAR+BARU+BLOK+A++NO.+6+TANJUNG+UBAN%2C+KEPRI%2C+INDONESIA\",\"vendorActivateStatus\":true,\"vendorFax\":\"\"},{\"vendorEmail\":\"\",\"vendorID\":\"0000000045ebca930145eeded24200dd\",\"currencyid\":\"13\",\"vendorName\":\"CV.+SAL+ABADI\",\"vendorContactNo\":\"081364468545\",\"vendorDebitTerm\":\"0000000045e8029f0145ea49830e0003\",\"vendorAddress\":\"Komp.+Perum+Taman+Surya+Indah+Blok+B%2F06+-+Seri+Kuala+Lobam+Kepulauan+Riau+29152%2C+BINTAN%2C+INDONESIA\",\"vendorActivateStatus\":true,\"vendorFax\":\"\"},{\"vendorEmail\":\"\",\"vendorID\":\"0000000045ebca930145eeded24500de\",\"currencyid\":\"13\",\"vendorName\":\"CV.+SURYA+CITRA\",\"vendorContactNo\":\"0771 483836\",\"vendorDebitTerm\":\"0000000045e8029f0145ea49830e0003\",\"vendorAddress\":\"PERUMAHAN+GRIYA+BIMA+KENCANA+BLOK+B%2F03%2C+TANJUNG+UBAN+-+BINTAN+BINTAN%2C+INDONESIA\",\"vendorActivateStatus\":true,\"vendorFax\":\"\"},{\"vendorEmail\":\"tuenparis@gmail.com\",\"vendorID\":\"402881e64624d260014626a2b7650008\",\"currencyid\":\"6\",\"vendorName\":\"CV.TUEN+PARIS+ENGINEERING\",\"vendorContactNo\":\"081364579819\",\"vendorDebitTerm\":\"0000000045e8029f0145ea49830e0003\",\"vendorAddress\":\"KOMPLEK+PRIMA+SEJATI%0ABLOK+B+%2C+NO+10%0ABATAM+CENTER%0AINDONESIA\",\"vendorActivateStatus\":true,\"vendorFax\":\"\"},{\"vendorEmail\":\"\",\"vendorID\":\"0000000045ebca930145eeded26000e3\",\"currencyid\":\"6\",\"vendorName\":\"DRS+BERNARDI++%26+REKAN\",\"vendorContactNo\":\"0770 612861\",\"vendorDebitTerm\":\"0000000045e8029f0145ea49830e0003\",\"vendorAddress\":\"WISMA+BATAMINDO+%2303-19+BATAM%2C+INDONESIA\",\"vendorActivateStatus\":true,\"vendorFax\":\"\"},{\"vendorEmail\":\"\",\"vendorID\":\"0000000045ebca930145eeded2a900f4\",\"currencyid\":\"13\",\"vendorName\":\"PT+BINTAN+INTI+INDUSTRIAL+ESTATE+%28IDR%29\",\"vendorContactNo\":\"0770 696833\",\"vendorDebitTerm\":\"0000000045e8029f0145ea49830e0003\",\"vendorAddress\":\"JALAN+TANJUNG+LOBAM+PO+BOX+020+LOBAM+29154%2C+BINTAN%2C+INDONESIA\",\"vendorActivateStatus\":true,\"vendorFax\":\"\"},{\"vendorEmail\":\"\",\"vendorID\":\"0000000045ebca930145eeded23e00dc\",\"currencyid\":\"6\",\"vendorName\":\"PT+BINTAN+INTI+INDUSTRIAL+ESTATE+%28SGD%29\",\"vendorContactNo\":\"0770 696833\",\"vendorDebitTerm\":\"0000000045e8029f0145ea49830e0003\",\"vendorAddress\":\"JALAN+TANJUNG+LOBAM+PO+BOX+020+LOBAM+29154%2C+BINTAN%2C+INDONESIA\",\"vendorActivateStatus\":true,\"vendorFax\":\"\"},{\"vendorEmail\":\"\",\"vendorID\":\"0000000045ebca930145eeded2ae00f5\",\"currencyid\":\"13\",\"vendorName\":\"PT+BUANA+KALPATARU+KONSULTAN\",\"vendorContactNo\":\"0771 8037982\",\"vendorDebitTerm\":\"0000000045e8029f0145ea49830e0003\",\"vendorAddress\":\"JALAN+D.I.+PANJAITAN+KM.+9%2C+TAMAN+GURINDAM+PERMAI+BLOK+D+NO.+1+TANJUNG+PINANG%2C+BINTAN%2C+INDONESIA\",\"vendorActivateStatus\":true,\"vendorFax\":\"\"},{\"vendorEmail\":\"\",\"vendorID\":\"0000000045ebca930145eeded28900ed\",\"currencyid\":\"6\",\"vendorName\":\"PT+BUMI+BENTENG+LESTARI+BATAM\",\"vendorContactNo\":\"0778 7517210\",\"vendorDebitTerm\":\"0000000045e8029f0145ea49830e0003\",\"vendorAddress\":\"KOMP.+RUKO+MEGA+LEGENDA+BLOK+E1-33+BATAM+CENTRE%2C+INDONESIA\",\"vendorActivateStatus\":true,\"vendorFax\":\"\"},{\"vendorEmail\":\"\",\"vendorID\":\"402881e6466435930146661d3aba0a4e\",\"currencyid\":\"1\",\"vendorName\":\"PT+CCI+-+PMIT\",\"vendorContactNo\":\"\",\"vendorDebitTerm\":\"0000000045e8029f0145ea49830e0006\",\"vendorAddress\":\"LOT+SD37+Bintan+Industrial+Estate+Lobam%0APulau+Bintan%2C+Indonesia\",\"vendorActivateStatus\":true,\"vendorFax\":\"\"},{\"vendorEmail\":\"\",\"vendorID\":\"0000000045ebca930145eeded26d00e6\",\"currencyid\":\"13\",\"vendorName\":\"PT+DIGISI+INDONESIA\",\"vendorContactNo\":\"085264442062\",\"vendorDebitTerm\":\"0000000045e8029f0145ea49830e0003\",\"vendorAddress\":\"KUANTAN+INDAH+BLOK+I+NO+12A%2C+BATU+5+ATAS+TANJUNG+PINANG%2C+BINTAN%2C+INDONESIA\",\"vendorActivateStatus\":true,\"vendorFax\":\"\"},{\"vendorEmail\":\"\",\"vendorID\":\"0000000045ebca930145eeded22800d7\",\"currencyid\":\"6\",\"vendorName\":\"PT+FATHAN+AGUNG\",\"vendorContactNo\":\"0778 465610/465180\",\"vendorDebitTerm\":\"0000000045e8029f0145ea49830e0003\",\"vendorAddress\":\"KOMPLEK+GUDANG+I+BLOK+A+NO+5\",\"vendorActivateStatus\":false,\"vendorFax\":\"\"},{\"vendorEmail\":\"\",\"vendorID\":\"0000000045ebca930145eeded28100eb\",\"currencyid\":\"13\",\"vendorName\":\"PT+INDONESIA+BELATEK+FORMAXI\",\"vendorContactNo\":\"0231 71734585\",\"vendorDebitTerm\":\"0000000045e8029f0145ea49830e0003\",\"vendorAddress\":\"KOMP+MERPATI%2C+JL+EBONY+C2%2C+PABEAN+-+SIDOARJO+61253\",\"vendorActivateStatus\":true,\"vendorFax\":\"\"},{\"vendorEmail\":\"\",\"vendorID\":\"0000000045ebca930145eeded26400e4\",\"currencyid\":\"13\",\"vendorName\":\"PT+INFORSYS+INDONESIA\",\"vendorContactNo\":\"0778 472111\",\"vendorDebitTerm\":\"0000000045e8029f0145ea49830e0003\",\"vendorAddress\":\"JLN+LAKSAMANA+BINTAN%2C+KOMP+EXECUTIVE+CENTRE+BLK+2+NO+5-6+BATAM%2C+INDONESIA\",\"vendorActivateStatus\":true,\"vendorFax\":\"\"},{\"vendorEmail\":\"\",\"vendorID\":\"0000000045ebca930145eeded23700da\",\"currencyid\":\"6\",\"vendorName\":\"PT+MOORES+ROWLAND+CONSULTING\",\"vendorContactNo\":\"0770 612861/612862/612863\",\"vendorDebitTerm\":\"0000000045e8029f0145ea49830e0003\",\"vendorAddress\":\"WISMA+BATAMINDO+%2303-19+JL+RASAMALA+NO+1+BATAMINDO+INDUSTRIAL+PARK%2C+INDONESIA\",\"vendorActivateStatus\":true,\"vendorFax\":\"\"},{\"vendorEmail\":\"\",\"vendorID\":\"0000000045ebca930145eeded27d00ea\",\"currencyid\":\"13\",\"vendorName\":\"PT+NEVILLE-CLARKE+INDONESIA\",\"vendorContactNo\":\"0221 83709100\",\"vendorDebitTerm\":\"0000000045e8029f0145ea49830e0003\",\"vendorAddress\":\"MENARA+MTH+11TH+FLOOR%2C+SUITE+02+JL+LETJEN+MT+HARYONO+KAV+23%2C+JAKARTA+12820%2C+INDONESIA\",\"vendorActivateStatus\":true,\"vendorFax\":\"\"},{\"vendorEmail\":\"\",\"vendorID\":\"0000000045ebca930145eeded2b800f7\",\"currencyid\":\"13\",\"vendorName\":\"PT+PANCA+SINERGY+UTAMA\",\"vendorContactNo\":\"0778 7372204/7372205\",\"vendorDebitTerm\":\"0000000045e8029f0145ea49830e0003\",\"vendorAddress\":\"KOMP.RUKO+TAMAN+NIAGA+SUKAJADI+BLOK+K+NO.10+BATAM+29463\",\"vendorActivateStatus\":true,\"vendorFax\":\"\"},{\"vendorEmail\":\"\",\"vendorID\":\"0000000045ebca930145eeded26900e5\",\"currencyid\":\"13\",\"vendorName\":\"PT+SUCOFINDO\",\"vendorContactNo\":\"0778 456575\",\"vendorDebitTerm\":\"0000000045e8029f0145ea49830e0003\",\"vendorAddress\":\"GRAHA+SUCOFINDO+JL+RAYA+PASAR+MINGGU+KAV+34+PANCORAN+JAKARTA+SELATAN+12780+INDONESIA\",\"vendorActivateStatus\":true,\"vendorFax\":\"\"},{\"vendorEmail\":\"\",\"vendorID\":\"0000000045ebca930145eeded27900e9\",\"currencyid\":\"13\",\"vendorName\":\"PT+TACHI+JINO\",\"vendorContactNo\":\"0778 474442\",\"vendorDebitTerm\":\"0000000045e8029f0145ea49830e0003\",\"vendorAddress\":\"KOMPLEK+TAMAN+MARCHELIA+BLOCK+A+NO+220+RIAU+29152%2C+BATAM+CENTRE%2C+INDONESIA\",\"vendorActivateStatus\":true,\"vendorFax\":\"\"},{\"vendorEmail\":\"\",\"vendorID\":\"0000000045ebca930145eeded23400d9\",\"currencyid\":\"13\",\"vendorName\":\"PT+TUNASKARYA+INDOSWASTA+%28IDR%29\",\"vendorContactNo\":\"0770 611937\",\"vendorDebitTerm\":\"0000000045e8029f0145ea49830e0003\",\"vendorAddress\":\"JL+ANGSANA%2C+LOT+306+BATAMINDO+INDUSTRIAL+PARK%2C+INDONESIA\",\"vendorActivateStatus\":true,\"vendorFax\":\"\"},{\"vendorEmail\":\"\",\"vendorID\":\"0000000045ebca930145eeded2a500f3\",\"currencyid\":\"6\",\"vendorName\":\"PT+TUNASKARYA+INDOSWASTA+%28SGD%29\",\"vendorContactNo\":\"0770 611937\",\"vendorDebitTerm\":\"0000000045e8029f0145ea49830e0003\",\"vendorAddress\":\"JL+ANGSANA%2C+LOT+306+BATAMINDO+INDUSTRIAL+PARK%2C+INDONESIA\",\"vendorActivateStatus\":true,\"vendorFax\":\"\"},{\"vendorEmail\":\"\",\"vendorID\":\"0000000045ebca930145eeded2b300f6\",\"currencyid\":\"13\",\"vendorName\":\"PT+UNIVERSAL+KARYA+MANDIRI\",\"vendorContactNo\":\"0778 7372021\",\"vendorDebitTerm\":\"0000000045e8029f0145ea49830e0003\",\"vendorAddress\":\"JL.+JEND.+A+YANI%2C+KOMP.+RUKO+TAMAN+NIAGA+BLOK+C+NO.+5+BATAM\",\"vendorActivateStatus\":true,\"vendorFax\":\"\"},{\"vendorEmail\":\"\",\"vendorID\":\"0000000045ebca930145eeded22100d6\",\"currencyid\":\"6\",\"vendorName\":\"PT.+ARTHABUMI+SINARINDO+%28ABSO%29\",\"vendorContactNo\":\"0778 478899\",\"vendorDebitTerm\":\"0000000045e8029f0145ea49830e0003\",\"vendorAddress\":\"KOMPLEKS+LIMINDO+TRADE+CENTRE+BLOK+B+NO.+3+BATAM+CENTRE%2C+INDONESIA\",\"vendorActivateStatus\":true,\"vendorFax\":\"\"},{\"vendorEmail\":\"\",\"vendorID\":\"0000000045ebca930145eeded2bd00f8\",\"currencyid\":\"13\",\"vendorName\":\"PT.+ASURANSI+RAMA+SATRIA+WIBAWA\",\"vendorContactNo\":\"0771 27998\",\"vendorDebitTerm\":\"0000000045e8029f0145ea49830e0003\",\"vendorAddress\":\"JL.+GATOT+SUBROTO+KM.+5+NO.+8+TANJUNG+PINANG%2C+BINTAN%2C+INDONESIA\",\"vendorActivateStatus\":true,\"vendorFax\":\"\"},{\"vendorEmail\":\"\",\"vendorID\":\"0000000045ebca930145eeded1fd00ca\",\"currencyid\":\"13\",\"vendorName\":\"PT.+BATAM+BINTAN+TELEKOMUNIKASI\",\"vendorContactNo\":\"0770 612300\",\"vendorDebitTerm\":\"0000000045e8029f0145ea49830e0003\",\"vendorAddress\":\"JL+MARKISA%2C+BATAM+29433+BATAMINDO+INDUSTRIAL+PARK%2C+INDONESIA\",\"vendorActivateStatus\":true,\"vendorFax\":\"\"},{\"vendorEmail\":\"\",\"vendorID\":\"0000000045ebca930145eeded28e00ee\",\"currencyid\":\"1\",\"vendorName\":\"PT.+BATAM+BINTAN+TELEKOMUNIKASI\",\"vendorContactNo\":\"0770 612300\",\"vendorDebitTerm\":\"0000000045e8029f0145ea49830e0003\",\"vendorAddress\":\"JL+MARKISA%2C+BATAM+29433+BATAMINDO+INDUSTRIAL+PARK%2C+INDONESIA\",\"vendorActivateStatus\":true,\"vendorFax\":\"\"},{\"vendorEmail\":\"\",\"vendorID\":\"0000000045ebca930145eeded24a00df\",\"currencyid\":\"13\",\"vendorName\":\"PT.+BIMASAKTI+ASIALOGISTIK\",\"vendorContactNo\":\"0778 7510345\",\"vendorDebitTerm\":\"0000000045e8029f0145ea49830e0003\",\"vendorAddress\":\"KAWASAN+INDUSTRI+BINTAN+INTI+INDUSTRIAL+ESTATE+LOBAM+-+P+BINTAN+BINTAN%2C+INDONESIA\",\"vendorActivateStatus\":true,\"vendorFax\":\"\"},{\"vendorEmail\":\"\",\"vendorID\":\"0000000045ebca930145eeded20c00d0\",\"currencyid\":\"13\",\"vendorName\":\"PT.+CHLONINDO+PERMATA+INDAH\",\"vendorContactNo\":\"0771 483035\",\"vendorDebitTerm\":\"0000000045e8029f0145ea49830e0003\",\"vendorAddress\":\"JLN+PERMAISURI+TANJUNG+UBAN%2C+KEPRI%2C+INDONESIA\",\"vendorActivateStatus\":true,\"vendorFax\":\"\"},{\"vendorEmail\":\"\",\"vendorID\":\"0000000045ebca930145eeded21700d3\",\"currencyid\":\"1\",\"vendorName\":\"PT.+DISAMTING+PRATAMA\",\"vendorContactNo\":\"0778 7372249\",\"vendorDebitTerm\":\"0000000045e8029f0145ea49830e0003\",\"vendorAddress\":\"Komplek+Taman+Niaga+Blok+N%2CNo+6%2C+SUKAJADI+BATAM%2C+RIAU+29461%2C+INDONESIA\",\"vendorActivateStatus\":false,\"vendorFax\":\"\"},{\"vendorEmail\":\"\",\"vendorID\":\"0000000045ebca930145eeded20100cc\",\"currencyid\":\"6\",\"vendorName\":\"PT.+DUTA+COMPUTER\",\"vendorContactNo\":\"0778 433007\",\"vendorDebitTerm\":\"0000000045e8029f0145ea49830e0003\",\"vendorAddress\":\"KOMPLEKS+EXECUTIVE+CENTRE+BLK+II+NO+1-2+JL+LAKSAMANA+BINTAN%2C+SEL+PANAS+BINTAN%2C+INDONESIA\",\"vendorActivateStatus\":true,\"vendorFax\":\"\"},{\"vendorEmail\":\"\",\"vendorID\":\"0000000045ebca930145eeded1ff00cb\",\"currencyid\":\"13\",\"vendorName\":\"PT.+ESCOTAMA++HANDAL+%28IDR%29\",\"vendorContactNo\":\"0771 482687\",\"vendorDebitTerm\":\"0000000045e8029f0145ea49830e0003\",\"vendorAddress\":\"JL+KAMPUNG+HARAPAN+NO+1%2C+TELOK+SASAH+BATAM%2C+INDONESIA\",\"vendorActivateStatus\":true,\"vendorFax\":\"\"},{\"vendorEmail\":\"\",\"vendorID\":\"0000000045ebca930145eeded29200ef\",\"currencyid\":\"6\",\"vendorName\":\"PT.+ESCOTAMA++HANDAL+%28SGD%29\",\"vendorContactNo\":\"0771 482687\",\"vendorDebitTerm\":\"0000000045e8029f0145ea49830e0003\",\"vendorAddress\":\"JL+KAMPUNG+HARAPAN+NO+1%2C+TELOK+SASAH+BATAM%2C+INDONESIA\",\"vendorActivateStatus\":true,\"vendorFax\":\"\"},{\"vendorEmail\":\"\",\"vendorID\":\"0000000045ebca930145eeded20900cf\",\"currencyid\":\"6\",\"vendorName\":\"PT.+IS+PREMIER+CONTAINER+BINTAN\",\"vendorContactNo\":\"0770 696688\",\"vendorDebitTerm\":\"0000000045e8029f0145ea49830e0003\",\"vendorAddress\":\"BINTAN+INDUSTRIAL+ESTATE%2C+JALAN+ASTER+BUNDARAN+TERRACE+LOT+T1+KEPRI+29154%2C+INDONESIA\",\"vendorActivateStatus\":true,\"vendorFax\":\"\"},{\"vendorEmail\":\"\",\"vendorID\":\"0000000045ebca930145eeded21a00d4\",\"currencyid\":\"6\",\"vendorName\":\"PT.+TECHNOPURE+INTI+PERKASA\",\"vendorContactNo\":\"021-54355622/54353550\",\"vendorDebitTerm\":\"0000000045e8029f0145ea49830e0003\",\"vendorAddress\":\"KOMPLEK+MUTIARA+TAMAN+PALEM+BLOK+C19+NO.50+CENGKARENG+JAKARTA+BARAT%2C+11730+INDONESIA\",\"vendorActivateStatus\":false,\"vendorFax\":\"\"},{\"vendorEmail\":\"\",\"vendorID\":\"0000000045ebca930145eeded24f00e0\",\"currencyid\":\"13\",\"vendorName\":\"PT.+TRI+MULIA+BATAM\",\"vendorContactNo\":\"0778 7896400\",\"vendorDebitTerm\":\"0000000045e8029f0145ea49830e0003\",\"vendorAddress\":\"KOMPLEK+ACCELLENCE+ENTERPRISE+BLOK+B+NO+3\",\"vendorActivateStatus\":true,\"vendorFax\":\"\"},{\"vendorEmail\":\"\",\"vendorID\":\"0000000045ebca930145eeded22f00d8\",\"currencyid\":\"6\",\"vendorName\":\"PT.PUTRA+BATAM+JASA+MANDIRI+UTAMA\",\"vendorContactNo\":\"0778 413823\",\"vendorDebitTerm\":\"0000000045e8029f0145ea49830e0003\",\"vendorAddress\":\"JL+YOS+SUDARSO+%28SIMPANG+JL+KERAPU%29+BATU+AMPAR\",\"vendorActivateStatus\":true,\"vendorFax\":\"\"},{\"vendorEmail\":\"\",\"vendorID\":\"0000000045ebca930145eeded28500ec\",\"currencyid\":\"13\",\"vendorName\":\"SIGMA++GLOBAL+SOLUTION+BATAM\",\"vendorContactNo\":\"085356592112\",\"vendorDebitTerm\":\"0000000045e8029f0145ea49830e0003\",\"vendorAddress\":\"KOMPLEK+TAMAN+MARCHELIA+BLOCK+C+NO+16+BATAM+CENTRE%2C+INDONESIA\",\"vendorActivateStatus\":true,\"vendorFax\":\"\"},{\"vendorEmail\":\"\",\"vendorID\":\"0000000045ebca930145eeded25600e1\",\"currencyid\":\"13\",\"vendorName\":\"TOKO+INTI+SURYA\",\"vendorContactNo\":\"0771 82136\",\"vendorDebitTerm\":\"0000000045e8029f0145ea49830e0003\",\"vendorAddress\":\"JLN+INDUNSURI+BLOCK+B1+NO+9+BATAM+CENTRE%2C+INDONESIA\",\"vendorActivateStatus\":true,\"vendorFax\":\"\"},{\"vendorEmail\":\"\",\"vendorID\":\"0000000045ebca930145eeded21400d2\",\"currencyid\":\"13\",\"vendorName\":\"TOKO+SARI+BUMI+%28IDR%29\",\"vendorContactNo\":\"0771 482882\",\"vendorDebitTerm\":\"0000000045e8029f0145ea49830e0003\",\"vendorAddress\":\"JALAN+PERMAISURI+TANJUNG+UBAN%2C+BINTAN%2C+INDONESIA\",\"vendorActivateStatus\":true,\"vendorFax\":\"\"},{\"vendorEmail\":\"\",\"vendorID\":\"0000000045ebca930145eeded2a000f2\",\"currencyid\":\"6\",\"vendorName\":\"TOKO+SARI+BUMI+%28SGD%29\",\"vendorContactNo\":\"0771 482882\",\"vendorDebitTerm\":\"0000000045e8029f0145ea49830e0003\",\"vendorAddress\":\"JALAN+PERMAISURI+TANJUNG+UBAN%2C+BINTAN%2C+INDONESIA\",\"vendorActivateStatus\":true,\"vendorFax\":\"\"},{\"vendorEmail\":\"\",\"vendorID\":\"0000000045ebca930145eeded23b00db\",\"currencyid\":\"6\",\"vendorName\":\"TOLL+LOGISTICS+%28ASIA%29+LIMITED\",\"vendorContactNo\":\"+65 62622206 / 62622623\",\"vendorDebitTerm\":\"0000000045e8029f0145ea49830e0003\",\"vendorAddress\":\"21+JALAN+BUROH+%2307-00+LOGISTICS+21+SINGAPORE+619478\",\"vendorActivateStatus\":true,\"vendorFax\":\"\"}]}",
    "success":true
}